dreqPy/__init__.py
dreqPy/dreq.py
dreqPy/dreqCmdl.py
dreqPy/fgrid.py
dreqPy/htmlTemplates.py
dreqPy/makeTables.py
dreqPy/misc_utils.py
dreqPy/overviewTabs.py
dreqPy/packageConfig.py
dreqPy/realmAnal.py
dreqPy/rvgExtraTable.py
dreqPy/scope.py
dreqPy/scope_utils.py
dreqPy/simpleCheck.py
dreqPy/table_utils.py
dreqPy/utilP3.py
dreqPy/utilities.py
dreqPy/utils_dreq.py
dreqPy/versionConfig.py
dreqPy/vocabDemo.py
dreqPy/volsum.py
dreqPy/vrev.py
dreqPy/docs/BlockSchema.csv
dreqPy/docs/CMIP6_MIP_tables.xlsx
dreqPy/docs/dc1.xsd
dreqPy/docs/dreq.xml
dreqPy/docs/dreq2Defn.xml
dreqPy/docs/dreq2Sample.xml
dreqPy/docs/dreq2Schema.xsd
dreqPy/docs/dreqML.pdf
dreqPy/docs/dreqManifest.txt
dreqPy/docs/dreqPy.pdf
dreqPy/docs/dreqSample.xml
dreqPy/docs/dreqSupp.xml
dreqPy/docs/dreqSuppDefn.xml
dreqPy/docs/dreqSuppSchema.xsd
dreqPy/docs/md5Manifest.txt
dreqPy/docs/pav.xsd
dreqPy/docs/sfheadings.csv
dreqPy/docs/vocab.xml
dreqPy/docs/vocabDefn.xml
dreqPy/docs/vocabFrameworkSchema_01beta.xsd
dreqPy/docs/vocabSample.xml
dreqPy/docs/vocabSchema.xsd
dreqPy/docs/xlink.xsd
dreqPy/docs/xml.xsd
dreqPy/examples/__init__.py
dreqPy/examples/ex002.py
dreqPy/examples/ex101.py
dreqPy/examples/ex102.py
dreqPy/examples/ex202.py
dreqPy/examples/ex203.py
dreqPy/extensions/__init__.py
dreqPy/extensions/collect.py
dreqPy/extensions/versions.py
dreqPy/utilP2/__init__.py
dreqPy/utilP2/util.py
dreqPy-1.2.0.data/data/LICENSE
dreqPy-1.2.0.dist-info/LICENSE
dreqPy-1.2.0.dist-info/METADATA
dreqPy-1.2.0.dist-info/WHEEL
dreqPy-1.2.0.dist-info/entry_points.txt
dreqPy-1.2.0.dist-info/top_level.txt
dreqPy-1.2.0.dist-info/RECORD
