Metadata-Version: 2.1
Name: dreqPy
Version: 1.2.0
Summary: CMIP6 Data Request Python API
Home-page: http://proj.badc.rl.ac.uk/svn/exarch/CMIP6dreq/tags/01.02.00
Author: Martin Juckes
Author-email: martin.juckes@stfc.ac.uk
Maintainer: Martin Juckes
Maintainer-email: martin.juckes@stfc.ac.uk
License: BSD
Keywords: CMIP6
Platform: UNKNOWN
Classifier: Development Status :: 4 - Beta
Classifier: Intended Audience :: Developers
Classifier: Natural Language :: English
Classifier: License :: OSI Approved :: MIT License
Classifier: Operating System :: OS Independent
Classifier: Programming Language :: Python
Classifier: Programming Language :: Python :: 2
Classifier: Programming Language :: Python :: 2.7
Classifier: Programming Language :: Python :: 3
Classifier: Topic :: Software Development :: Libraries :: Python Modules
